{
  "Version": 1,
  "ID": "f8821a47-6add-422d-a5a4-a50478b774d7",
  "Name": "Dott. CITTERIO TIZIANO",
  "Alias": "dott_citterio_tiziano",
  "Note": "",
  "Image": "",
  "Level1": [
    {
      "Value": "Lissone",
      "Alias": "lissone"
    }
  ],
  "Level2": [
    {
      "Value": "Medico di famiglia",
      "Alias": "medico"
    }
  ],
  "Adresses": [
    {
      "Title": "Studio",
      "Value": "Via Giovanni Orelli, 28\r\n20851 Lissone MB",
      "Latitude": "45.612623",
      "Longitude": "9.243692",
      "Note": ""
    }
  ],
  "Contacts": [
    {
      "Title": "per consigli:",
      "Value": "039 461222",
      "Note": "orario ambulatorio",
      "Type": 0
    },
    {
      "Title": "per visite a domicilio:",
      "Value": "039 461222",
      "Note": "8.00 - 10.00",
      "Type": 0
    },
    {
      "Title": "Per appuntamento",
      "Value": "039 461222",
      "Note": "8.00 - 10.00",
      "Type": 0
    }
  ],
  "Calendar": [
    {
      "Title": "Orario ambulatorio",
      "Note": "",
      "WeekDays": [
        {
          "WeekDay": 1,
          "Schedules": [
            {
              "StartTime": "15:30",
              "EndTime": "19:00",
              "Note": ""
            }
          ]
        },
        {
          "WeekDay": 2,
          "Schedules": [
            {
              "StartTime": "10:00",
              "EndTime": "12:30",
              "Note": ""
            }
          ]
        },
        {
          "WeekDay": 3,
          "Schedules": [
            {
              "StartTime": "15:30",
              "EndTime": "18:00",
              "Note": ""
            }
          ]
        },
        {
          "WeekDay": 4,
          "Schedules": [
            {
              "StartTime": "10:00",
              "EndTime": "12:30",
              "Note": ""
            }
          ]
        },
        {
          "WeekDay": 5,
          "Schedules": [
            {
              "StartTime": "15:30",
              "EndTime": "19:00",
              "Note": ""
            }
          ]
        }
      ],
      "Days": []
    }
  ],
  "Notes": [],
  "Google": {
    "ID": "",
    "Link": ""
  },
  "Facebook": {
    "ID": "",
    "Link": ""
  }
}