{
  "Version": 1,
  "ID": "6108bb48-4c18-4db2-b56a-e5412d8d456c",
  "Name": "Dott. Manzoni Luigi Maria",
  "Alias": "dott_manzoni_luigi_maria",
  "Note": "",
  "Image": "",
  "Level1": [
    {
      "Value": "Nova Milanese",
      "Alias": "nova-milanese"
    }
  ],
  "Level2": [
    {
      "Value": "Medico di famiglia",
      "Alias": "medico"
    }
  ],
  "Adresses": [
    {
      "Title": "Studio",
      "Value": "Via Brodolini, 1  20834 NOVA MILANESE",
      "Latitude": "45.583157",
      "Longitude": "9.196531",
      "Note": ""
    }
  ],
  "Contacts": [
    {
      "Title": "Per appuntamento",
      "Value": "02/33105800",
      "Note": "",
      "Type": 0
    },
    {
      "Title": "per visite a domicilio:",
      "Value": "335 71 04 889",
      "Note": "da lun a ven dalle 08.00 alle 10.00",
      "Type": 0
    },
    {
      "Title": "per consigli:",
      "Value": "0362/43186",
      "Note": "da lun a ven durante l'orario di ambulatorio",
      "Type": 0
    }
  ],
  "Calendar": [
    {
      "Title": "Orario ambulatorio",
      "Note": "",
      "WeekDays": [
        {
          "WeekDay": 1,
          "Schedules": [
            {
              "StartTime": "15:00",
              "EndTime": "19:00",
              "Note": ""
            }
          ]
        },
        {
          "WeekDay": 2,
          "Schedules": [
            {
              "StartTime": "08:30",
              "EndTime": "12:30",
              "Note": ""
            }
          ]
        },
        {
          "WeekDay": 3,
          "Schedules": [
            {
              "StartTime": "15:00",
              "EndTime": "19:00",
              "Note": ""
            }
          ]
        },
        {
          "WeekDay": 4,
          "Schedules": [
            {
              "StartTime": "08:30",
              "EndTime": "12:30",
              "Note": ""
            }
          ]
        },
        {
          "WeekDay": 5,
          "Schedules": [
            {
              "StartTime": "15:00",
              "EndTime": "19:00",
              "Note": ""
            }
          ]
        }
      ],
      "Days": []
    }
  ],
  "Notes": [],
  "Google": {
    "ID": "",
    "Link": ""
  },
  "Facebook": {
    "ID": "",
    "Link": ""
  }
}