{
  "Version": 1,
  "ID": "df720823-b409-4b7d-99e6-01fedd474f4c",
  "Name": "Scuola Dell'infanzia Parrocchiale San Rocco",
  "Alias": "scuola_dellinfanzia_parrocchiale_san_rocco",
  "Level1": [
    {
      "Value": "Monza",
      "Alias": "monza"
    }
  ],
  "Level2": [
    {
      "Value": "Scuola materna",
      "Alias": "scuola_materna"
    }
  ],
  "Adresses": [
    {
      "Title": "Indirizzo",
      "Value": "VIA MONTE SANTO 2 MONZA",
      "Note": "",
      "Latitude": "45.562891",
      "Longitude": "9.265208"
    }
  ],
  "Contacts": [
    {
      "Title": "Email",
      "Value": "scuolabimbi.srmonza@alice.it",
      "Note": "",
      "Type": 1
    },
    {
      "Title": "Telefono",
      "Value": "0392180078",
      "Note": "",
      "Type": 0
    }
  ]
}