{
  "Version": 1,
  "ID": "eccaa241-1428-4f75-9c44-b0e61069fa17",
  "Name": "Dott. Canali Raffaele",
  "Alias": "dott_canali_raffaele",
  "Note": "",
  "Image": "",
  "Level1": [
    {
      "Value": "Desio",
      "Alias": "desio"
    }
  ],
  "Level2": [
    {
      "Value": "Medico di famiglia",
      "Alias": "medico"
    }
  ],
  "Adresses": [
    {
      "Title": "Studio",
      "Value": "Via Guglielmo Oberdan, 12\r\n20832 Desio MB",
      "Latitude": "45.621255",
      "Longitude": "9.207413",
      "Note": ""
    }
  ],
  "Contacts": [
    {
      "Title": "per visite a domicilio:",
      "Value": "0362/624618",
      "Note": "da lun a ven dalle 08.00 alle 10.00 ",
      "Type": 0
    },
    {
      "Title": "per consigli:",
      "Value": "339 2084791",
      "Note": "lun-mar-giov 16.30 - 18.30 mer-ven 10.30 - 12.30 ",
      "Type": 0
    },
    {
      "Title": "Per appuntamento",
      "Value": "0362/624618",
      "Note": "da lun a ven dalle 08.00 alle 10.00 ",
      "Type": 0
    }
  ],
  "Calendar": [
    {
      "Title": "Orario ambulatorio",
      "Note": "",
      "WeekDays": [
        {
          "WeekDay": 1,
          "Schedules": [
            {
              "StartTime": "15:30",
              "EndTime": "18:30",
              "Note": ""
            }
          ]
        },
        {
          "WeekDay": 2,
          "Schedules": [
            {
              "StartTime": "15:30",
              "EndTime": "18:30",
              "Note": ""
            }
          ]
        },
        {
          "WeekDay": 3,
          "Schedules": [
            {
              "StartTime": "10:00",
              "EndTime": "13:00",
              "Note": ""
            }
          ]
        },
        {
          "WeekDay": 4,
          "Schedules": [
            {
              "StartTime": "15:30",
              "EndTime": "18:30",
              "Note": ""
            }
          ]
        },
        {
          "WeekDay": 5,
          "Schedules": [
            {
              "StartTime": "10:00",
              "EndTime": "13:00",
              "Note": ""
            }
          ]
        }
      ],
      "Days": []
    }
  ],
  "Notes": [],
  "Google": {
    "ID": "",
    "Link": ""
  },
  "Facebook": {
    "ID": "",
    "Link": ""
  }
}